colorsearch.py
colorsearch-1.0.2.data/data/share/applications/colorsearch.desktop
colorsearch-1.0.2.data/data/share/icons/hicolor/64x64/apps/colorsearch.svg
colorsearch-1.0.2.dist-info/licenses/LICENSE
colorsearch-1.0.2.dist-info/METADATA
colorsearch-1.0.2.dist-info/WHEEL
colorsearch-1.0.2.dist-info/entry_points.txt
colorsearch-1.0.2.dist-info/top_level.txt
colorsearch-1.0.2.dist-info/RECORD
