Metadata-Version: 2.4
Name: colorsearch
Version: 1.0.2
Summary: Search images and videos by dominant color (PyQt6)
Home-page: https://github.com/Zamanhuseyinli/colorsearch
Author: Zaman Huseyinli
Author-email: zamanhuseynli23@gmail.com
Project-URL: Source Code, https://github.com/Zamanhuseyinli/colorsearch
Project-URL: Bug Tracker, https://github.com/Zamanhuseyinli/colorsearch/issues
Classifier: Programming Language :: Python :: 3
Classifier: Environment :: X11 Applications :: Qt
Classifier: Operating System :: POSIX :: Linux
Classifier: Operating System :: MacOS
Classifier: Operating System :: Microsoft :: Windows
Classifier: Topic :: Multimedia :: Graphics
Classifier: License :: OSI Approved :: GNU General Public License v3 (GPLv3)
Requires-Python: >=3.8
License-File: LICENSE
Requires-Dist: Pillow>=9.0.0
Requires-Dist: PyQt6>=6.4.0
Dynamic: author
Dynamic: author-email
Dynamic: classifier
Dynamic: description
Dynamic: description-content-type
Dynamic: home-page
Dynamic: license-file
Dynamic: project-url
Dynamic: requires-dist
Dynamic: requires-python
Dynamic: summary
